simplemodule/__init__.py
simplemodule/add.py
simplemodule/subtract.py
simplemodule/extras/__init__.py
simplemodule/extras/divide.py
simplemodule/extras/multiply.py
simplemodule12asd812893193-0.0.1.dist-info/METADATA
simplemodule12asd812893193-0.0.1.dist-info/WHEEL
simplemodule12asd812893193-0.0.1.dist-info/top_level.txt
simplemodule12asd812893193-0.0.1.dist-info/RECORD
